datacontract/__init__.py
datacontract/api.py
datacontract/cli.py
datacontract/data_contract.py
datacontract/py.typed
datacontract/catalog/catalog.py
datacontract/engines/__init__.py
datacontract/engines/data_contract_checks.py
datacontract/engines/data_contract_test.py
datacontract/engines/datacontract/check_that_datacontract_contains_valid_servers_configuration.py
datacontract/engines/datacontract/check_that_datacontract_file_exists.py
datacontract/engines/fastjsonschema/check_jsonschema.py
datacontract/engines/fastjsonschema/s3/s3_read_files.py
datacontract/engines/soda/__init__.py
datacontract/engines/soda/check_soda_execute.py
datacontract/engines/soda/connections/athena.py
datacontract/engines/soda/connections/bigquery.py
datacontract/engines/soda/connections/databricks.py
datacontract/engines/soda/connections/duckdb_connection.py
datacontract/engines/soda/connections/impala.py
datacontract/engines/soda/connections/kafka.py
datacontract/engines/soda/connections/oracle.py
datacontract/engines/soda/connections/postgres.py
datacontract/engines/soda/connections/snowflake.py
datacontract/engines/soda/connections/sqlserver.py
datacontract/engines/soda/connections/trino.py
datacontract/export/__init__.py
datacontract/export/avro_exporter.py
datacontract/export/avro_idl_exporter.py
datacontract/export/bigquery_exporter.py
datacontract/export/custom_exporter.py
datacontract/export/data_caterer_exporter.py
datacontract/export/dbml_exporter.py
datacontract/export/dbt_exporter.py
datacontract/export/dcs_exporter.py
datacontract/export/dqx_exporter.py
datacontract/export/duckdb_type_converter.py
datacontract/export/excel_exporter.py
datacontract/export/exporter.py
datacontract/export/exporter_factory.py
datacontract/export/go_exporter.py
datacontract/export/great_expectations_exporter.py
datacontract/export/html_exporter.py
datacontract/export/iceberg_exporter.py
datacontract/export/jsonschema_exporter.py
datacontract/export/markdown_exporter.py
datacontract_cli-0.11.4.dist-info/licenses/LICENSE
datacontract_cli-0.11.4.dist-info/METADATA
datacontract_cli-0.11.4.dist-info/WHEEL
datacontract_cli-0.11.4.dist-info/entry_points.txt
datacontract_cli-0.11.4.dist-info/top_level.txt
datacontract_cli-0.11.4.dist-info/RECORD
