Metadata-Version: 2.4
Name: datacontract-cli
Version: 0.11.4
Summary: The datacontract CLI is an open source command-line tool for working with Data Contracts. It uses data contract YAML files to lint the data contract, connect to data sources and execute schema and quality tests, detect breaking changes, and export to different formats. The tool is written in Python. It can be used as a standalone CLI tool, in a CI/CD pipeline, or directly as a Python library.
Author-email: Jochen Christ <jochen.christ@innoq.com>, Stefan Negele <stefan.negele@innoq.com>, Simon Harrer <simon.harrer@innoq.com>
License-Expression: MIT
Project-URL: Homepage, https://cli.datacontract.com
Project-URL: Issues, https://github.com/datacontract/datacontract-cli/issues
Classifier: Programming Language :: Python :: 3
Classifier: Operating System :: OS Independent
Requires-Python: <3.13,>=3.10
License-File: LICENSE
Requires-Dist: typer<0.22,>=0.15.1
Requires-Dist: pydantic<2.13.0,>=2.8.2
Requires-Dist: pyyaml~=6.0.1
Requires-Dist: requests<2.33,>=2.31
Requires-Dist: fastjsonschema<2.22.0,>=2.19.1
Requires-Dist: pytz>=2024.1
Requires-Dist: python-multipart<1.0.0,>=0.0.20
Requires-Dist: rich<15.0,>=13.7
Requires-Dist: sqlglot<29.0.0,>=26.6.0
Requires-Dist: setuptools>=60
Requires-Dist: python-dotenv<2.0.0,>=1.0.0
Requires-Dist: boto3<2.0.0,>=1.34.41
Requires-Dist: Jinja2<4.0.0,>=3.1.5
Requires-Dist: jinja_partials<1.0.0,>=0.2.1
Requires-Dist: datacontract-specification<2.0.0,>=1.2.3
Requires-Dist: open-data-contract-standard<4.0.0,>=3.1.2
Provides-Extra: avro
Requires-Dist: avro==1.12.1; extra == "avro"
Provides-Extra: bigquery
Requires-Dist: soda-core-bigquery<3.6.0,>=3.3.20; extra == "bigquery"
Provides-Extra: csv
Requires-Dist: pandas>=2.0.0; extra == "csv"
Provides-Extra: excel
Requires-Dist: openpyxl<4.0.0,>=3.1.5; extra == "excel"
Provides-Extra: databricks
Requires-Dist: soda-core-spark-df<3.6.0,>=3.3.20; extra == "databricks"
Requires-Dist: soda-core-spark[databricks]<3.6.0,>=3.3.20; extra == "databricks"
Requires-Dist: databricks-sql-connector<4.3.0,>=3.7.0; extra == "databricks"
Requires-Dist: databricks-sdk<0.78.0; extra == "databricks"
Requires-Dist: pyspark<5.0.0,>=3.5.0; extra == "databricks"
Requires-Dist: numpy<2.0.0,>=1.26.4; extra == "databricks"
Provides-Extra: iceberg
Requires-Dist: pyiceberg==0.10.0; extra == "iceberg"
Provides-Extra: kafka
Requires-Dist: datacontract-cli[avro]; extra == "kafka"
Requires-Dist: soda-core-spark-df<3.6.0,>=3.3.20; extra == "kafka"
Requires-Dist: pyspark<5.0.0,>=3.5.0; extra == "kafka"
Requires-Dist: numpy<2.0.0,>=1.26.4; extra == "kafka"
Provides-Extra: postgres
Requires-Dist: soda-core-postgres<3.6.0,>=3.3.20; extra == "postgres"
Provides-Extra: s3
Requires-Dist: s3fs<2026.0.0,>=2025.2.0; extra == "s3"
Requires-Dist: aiobotocore<3.2.0,>=2.17.0; extra == "s3"
Provides-Extra: snowflake
Requires-Dist: snowflake-connector-python[pandas]<4.2,>=3.6; extra == "snowflake"
Requires-Dist: soda-core-snowflake<3.6.0,>=3.3.20; extra == "snowflake"
Provides-Extra: sqlserver
Requires-Dist: soda-core-sqlserver<3.6.0,>=3.3.20; extra == "sqlserver"
Provides-Extra: oracle
Requires-Dist: soda-core-oracle<3.6.0,>=3.3.20; extra == "oracle"
Provides-Extra: athena
Requires-Dist: soda-core-athena<3.6.0,>=3.3.20; extra == "athena"
Provides-Extra: trino
Requires-Dist: soda-core-trino<3.6.0,>=3.3.20; extra == "trino"
Provides-Extra: dbt
Requires-Dist: dbt-core>=1.8.0; extra == "dbt"
Provides-Extra: dbml
Requires-Dist: pydbml>=1.1.1; extra == "dbml"
Provides-Extra: duckdb
Requires-Dist: duckdb<1.5.0,>=1.0.0; extra == "duckdb"
Requires-Dist: soda-core-duckdb<3.6.0,>=3.3.20; extra == "duckdb"
Provides-Extra: parquet
Requires-Dist: pyarrow>=18.1.0; extra == "parquet"
Provides-Extra: rdf
Requires-Dist: rdflib==7.5.0; extra == "rdf"
Provides-Extra: api
Requires-Dist: fastapi==0.121.2; extra == "api"
Requires-Dist: uvicorn==0.40.0; extra == "api"
Provides-Extra: protobuf
Requires-Dist: grpcio-tools>=1.53; extra == "protobuf"
Provides-Extra: all
Requires-Dist: datacontract-cli[api,athena,bigquery,csv,databricks,dbml,dbt,duckdb,excel,iceberg,kafka,oracle,parquet,postgres,protobuf,rdf,s3,snowflake,sqlserver,trino]; extra == "all"
Provides-Extra: dev
Requires-Dist: datacontract-cli[all]; extra == "dev"
Requires-Dist: httpx==0.28.1; extra == "dev"
Requires-Dist: kafka-python; extra == "dev"
Requires-Dist: minio==7.2.17; extra == "dev"
Requires-Dist: moto==5.1.18; extra == "dev"
Requires-Dist: pandas>=2.1.0; extra == "dev"
Requires-Dist: pre-commit<4.6.0,>=3.7.1; extra == "dev"
Requires-Dist: pytest; extra == "dev"
Requires-Dist: pytest-xdist; extra == "dev"
Requires-Dist: pymssql==2.3.9; extra == "dev"
Requires-Dist: ruff; extra == "dev"
Requires-Dist: testcontainers[kafka,minio,mssql,postgres]==4.13.3; extra == "dev"
Requires-Dist: trino==0.336.0; extra == "dev"
Dynamic: license-file
